essencebinder-0.1.1.dev0.dist-info/licenses/LICENSE.md
src/essencebinder/__bases__.py
src/essencebinder/__errors__.py
src/essencebinder/__init__.py
essencebinder-0.1.1.dev0.dist-info/METADATA
essencebinder-0.1.1.dev0.dist-info/WHEEL
essencebinder-0.1.1.dev0.dist-info/top_level.txt
essencebinder-0.1.1.dev0.dist-info/RECORD
