Metadata-Version: 2.4
Name: EssenceBinder
Version: 0.1.1.dev0
Summary: A brief description of EssenceBinder
Author-email: DirtyWork Solutions Limited <essencebinder@open.dirtywork.solutions>
License: MIT License
Project-URL: Homepage, https://open.dirtywork.solutions/EssenceBinder/
Project-URL: Repository, https://github.com/DirtyWork-Solutions/EssenceBinder
Classifier: Programming Language :: Python :: 3
Classifier: License :: OSI Approved :: MIT License
Classifier: Operating System :: OS Independent
Requires-Python: >=3.12
License-File: LICENSE.md
Requires-Dist: pyforged~=0.3.0.dev4
Provides-Extra: test
Requires-Dist: pytest>=6.0; extra == "test"
Requires-Dist: pytest-cov>=2.10; extra == "test"
Provides-Extra: dev
Provides-Extra: military
Provides-Extra: society
Provides-Extra: social
Provides-Extra: biology
Provides-Extra: industry
Provides-Extra: science
Provides-Extra: culture
Dynamic: license-file
